setup.py
incor/EventHandler.py
incor/__init__.py
incor/main.py
incor.egg-info/PKG-INFO
incor.egg-info/SOURCES.txt
incor.egg-info/dependency_links.txt
incor.egg-info/entry_points.txt
incor.egg-info/not-zip-safe
incor.egg-info/requires.txt
incor.egg-info/top_level.txt